certbot_deployer/__init__.py
certbot_deployer/__main__.py
certbot_deployer/meta.py
certbot_deployer/py.typed
certbot_deployer/deployer/__init__.py
certbot_deployer/deployer/py.typed
certbot_deployer/main/__init__.py
certbot_deployer/testing/__init__.py
certbot_deployer-2.1.1.dist-info/licenses/LICENSE
certbot_deployer-2.1.1.dist-info/METADATA
certbot_deployer-2.1.1.dist-info/WHEEL
certbot_deployer-2.1.1.dist-info/entry_points.txt
certbot_deployer-2.1.1.dist-info/top_level.txt
certbot_deployer-2.1.1.dist-info/RECORD
