Metadata-Version: 2.4
Name: certbot_deployer
Version: 2.1.1
Summary: certbot_deployer Pluggable certbot deploy hook framework
Home-page: https://github.com/theias/certbot_deployer
Author: IAS
Author-email: network@ias.edu
Project-URL: Documentation, https://theias.github.io/certbot_deployer/
Project-URL: Bug Tracker, https://github.com/theias/certbot_deployer/issues
Project-URL: Source, https://github.com/theias/certbot_deployer
Classifier: Programming Language :: Python :: 3
Classifier: License :: OSI Approved :: MIT License
Classifier: Operating System :: OS Independent
Requires-Python: >=3.9
License-File: LICENSE
Requires-Dist: cryptography<45.0.0,>=44.0.1
Requires-Dist: importlib_metadata<9.0.0,>=8.6.1; python_version < "3.10"
Provides-Extra: testing
Requires-Dist: pytest<9.0.0,>=8.3.4; extra == "testing"
Dynamic: license-file
